easyloader/__init__.py
easyloader/dataset/__init__.py
easyloader/dataset/array.py
easyloader/dataset/base.py
easyloader/dataset/df.py
easyloader/dataset/h5.py
easyloader/loader/__init__.py
easyloader/loader/array.py
easyloader/loader/base.py
easyloader/loader/df.py
easyloader/loader/h5.py
easyloader/utils/__init__.py
easyloader/utils/batch.py
easyloader/utils/grains.py
easyloader/utils/random.py
easyloader/utils/slices.py
easyloader/utils/typing.py
easyloader-1.0.1.dist-info/METADATA
easyloader-1.0.1.dist-info/WHEEL
easyloader-1.0.1.dist-info/top_level.txt
easyloader-1.0.1.dist-info/RECORD
