Metadata-Version: 2.1
Name: easyloader
Version: 1.0.1
Summary: Easily turn DFs, Arrays, and H5 files into PyTorch DataLoaders.
Author: Michael Peter Dunne
Classifier: Programming Language :: Python :: 3
Classifier: License :: OSI Approved :: MIT License
